.travis.yml
CHANGES.txt
COPYING.txt
MANIFEST.in
README.rst
requirements.txt
setup.cfg
setup.py
docs/Makefile
docs/conf.py
docs/index.rst
docs/kryptomime.rst
docs/make.bat
kryptomime/__init__.py
kryptomime/mail.py
kryptomime/pgp.py
kryptomime/smime.py
kryptomime/transport.py
kryptomime.egg-info/PKG-INFO
kryptomime.egg-info/SOURCES.txt
kryptomime.egg-info/dependency_links.txt
kryptomime.egg-info/requires.txt
kryptomime.egg-info/top_level.txt
tests/conftest.py
tests/keyring0
tests/keyring1
tests/secring0
tests/secring1
tests/test_gpg.py
tests/test_mail.py