Metadata-Version: 1.1
Name: kryptomime
Version: 0.4.0
Summary: Python support for E-Mail kryptography
Home-page: https://github.com/ttanner/kryptomime
Author: Thomas Tanner
Author-email: tanner@gmx.net
License: GPLv3+
Download-URL: https://github.com/ttanner/kryptomime/archive/master.zip
Platform: Linux
Platform: BSD
Platform: OSX
Platform: Windows
Classifier: Development Status :: 5 - Production/Stable
Classifier: Intended Audience :: Developers
Classifier: License :: OSI Approved :: GNU General Public License v3 or later (GPLv3+)
Classifier: Programming Language :: Python
Classifier: Programming Language :: Python :: 2
Classifier: Programming Language :: Python :: 3
Classifier: Programming Language :: Python :: 2.7
Classifier: Programming Language :: Python :: 3.0
Classifier: Programming Language :: Python :: 3.1
Classifier: Programming Language :: Python :: 3.2
Classifier: Programming Language :: Python :: 3.3
Classifier: Programming Language :: Python :: 3.4
Classifier: Topic :: Software Development :: Libraries :: Python Modules
Classifier: Topic :: Security :: Cryptography
Classifier: Topic :: Utilities
